dblp/__init__.py
dblp/dblpxml.py
dblp/webserver.py
dblpconf-0.0.3.dist-info/LICENSE
dblpconf-0.0.3.dist-info/METADATA
dblpconf-0.0.3.dist-info/WHEEL
dblpconf-0.0.3.dist-info/top_level.txt
dblpconf-0.0.3.dist-info/RECORD
