Metadata-Version: 2.1
Name: dblpconf
Version: 0.0.3
Summary: dblp conf
Home-page: https://github.com/WolfgangFahl/dblpconf
Author: Wolfgang Fahl
Author-email: wf@bitplan.com
License: Apache
Download-URL: https://github.com/WolfgangFahl/dblpconf
Project-URL: Documentation, http://wiki.bitplan.com/index.php/Dblpconf
Project-URL: Code, https://github.com/WolfgangFahl/dblpconf
Project-URL: Issue tracker, https://github.com/WolfgangFahl/dblpconf/issues
Platform: UNKNOWN
Classifier: Programming Language :: Python
Classifier: Programming Language :: Python :: 3.6
Classifier: Programming Language :: Python :: 3.7
Classifier: Programming Language :: Python :: 3.8
Classifier: Programming Language :: Python :: 3.9
Requires-Dist: pyFlaskBootstrap4
Requires-Dist: py-3rdparty-mediawiki (>=0.1.23)
Requires-Dist: pylodstorage
Requires-Dist: lxml
